nengo_loihi/__init__.py
nengo_loihi/block.py
nengo_loihi/compat.py
nengo_loihi/config.py
nengo_loihi/conv.py
nengo_loihi/decode_neurons.py
nengo_loihi/dvs.py
nengo_loihi/inputs.py
nengo_loihi/neurons.py
nengo_loihi/passthrough.py
nengo_loihi/probe.py
nengo_loihi/simulator.py
nengo_loihi/splitter.py
nengo_loihi/version.py
nengo_loihi/builder/__init__.py
nengo_loihi/builder/builder.py
nengo_loihi/builder/connection.py
nengo_loihi/builder/discretize.py
nengo_loihi/builder/ensemble.py
nengo_loihi/builder/inputs.py
nengo_loihi/builder/network.py
nengo_loihi/builder/node.py
nengo_loihi/builder/probe.py
nengo_loihi/builder/sparse_matrix.py
nengo_loihi/builder/split_blocks.py
nengo_loihi/builder/validate.py
nengo_loihi/builder/tests/__init__.py
nengo_loihi/builder/tests/test_builder.py
nengo_loihi/builder/tests/test_connection.py
nengo_loihi/builder/tests/test_discretize.py
nengo_loihi/builder/tests/test_inputs.py
nengo_loihi/builder/tests/test_sparse_matrix.py
nengo_loihi/builder/tests/test_split_blocks.py
nengo_loihi/builder/tests/test_validate.py
nengo_loihi/emulator/__init__.py
nengo_loihi/emulator/interface.py
nengo_loihi/emulator/tests/__init__.py
nengo_loihi/emulator/tests/test_interface.py
nengo_loihi/hardware/__init__.py
nengo_loihi/hardware/allocators.py
nengo_loihi/hardware/builder.py
nengo_loihi/hardware/interface.py
nengo_loihi/hardware/nxsdk_objects.py
nengo_loihi/hardware/nxsdk_shim.py
nengo_loihi/hardware/validate.py
nengo_loihi/hardware/snips/nengo_host.cpp.template
nengo_loihi/hardware/snips/nengo_io.c.template
nengo_loihi/hardware/snips/nengo_io.h.template
nengo_loihi/hardware/snips/nengo_learn.c.template
nengo_loihi/hardware/snips/nengo_learn.h.template
nengo_loihi/hardware/tests/__init__.py
nengo_loihi/hardware/tests/test_allocators.py
nengo_loihi/hardware/tests/test_interface.py
nengo_loihi/tests/__init__.py
nengo_loihi/tests/test_basic.py
nengo_loihi/tests/test_block.py
nengo_loihi/tests/test_config.py
nengo_loihi/tests/test_connection.py
nengo_loihi-1.1.0.dist-info/LICENSE.rst
nengo_loihi-1.1.0.dist-info/METADATA
nengo_loihi-1.1.0.dist-info/WHEEL
nengo_loihi-1.1.0.dist-info/entry_points.txt
nengo_loihi-1.1.0.dist-info/top_level.txt
nengo_loihi-1.1.0.dist-info/RECORD
