Metadata-Version: 2.1
Name: nengo-loihi
Version: 1.1.0
Summary: Run Nengo models on the Loihi chip
Home-page: https://www.nengo.ai/nengo-loihi
Author: Applied Brain Research
Author-email: info@appliedbrainresearch.com
License: Apache 2.0 license
Platform: UNKNOWN
Classifier: Development Status :: 4 - Beta
Classifier: Framework :: Nengo
Classifier: Intended Audience :: Science/Research
Classifier: License :: OSI Approved :: Apache Software License
Classifier: Operating System :: OS Independent
Classifier: Programming Language :: Python :: 3.10
Classifier: Programming Language :: Python :: 3.6
Classifier: Programming Language :: Python :: 3.7
Classifier: Programming Language :: Python :: 3.8
Classifier: Programming Language :: Python :: 3.9
Classifier: Topic :: Scientific/Engineering :: Artificial Intelligence
Requires-Python: >=3.6
License-File: LICENSE.rst
Requires-Dist: jinja2
Requires-Dist: nengo (>=3.1.0)
Requires-Dist: packaging
Requires-Dist: scipy (>=1.2.1)
Provides-Extra: all
Requires-Dist: nengo-sphinx-theme (>=0.7) ; extra == 'all'
Requires-Dist: numpydoc (>=0.6) ; extra == 'all'
Requires-Dist: sphinx (>=1.8) ; extra == 'all'
Requires-Dist: nengo-extras (>=0.5) ; extra == 'all'
Requires-Dist: networkx-metis (>=1.0) ; extra == 'all'
Requires-Dist: coverage (>=4.3) ; extra == 'all'
Requires-Dist: pytest (>=5.0.0) ; extra == 'all'
Requires-Dist: pytest-allclose (>=1.0.0) ; extra == 'all'
Requires-Dist: pytest-cov (>=2.6.0) ; extra == 'all'
Requires-Dist: pytest-plt (>=1.0.0) ; extra == 'all'
Requires-Dist: pytest-rng (>=1.0.0) ; extra == 'all'
Requires-Dist: pytest-xdist (>=2.0.0) ; extra == 'all'
Requires-Dist: matplotlib (>=2.0) ; extra == 'all'
Provides-Extra: docs
Requires-Dist: nengo-sphinx-theme (>=0.7) ; extra == 'docs'
Requires-Dist: numpydoc (>=0.6) ; extra == 'docs'
Requires-Dist: sphinx (>=1.8) ; extra == 'docs'
Provides-Extra: optional
Requires-Dist: nengo-extras (>=0.5) ; extra == 'optional'
Requires-Dist: networkx-metis (>=1.0) ; extra == 'optional'
Provides-Extra: tests
Requires-Dist: coverage (>=4.3) ; extra == 'tests'
Requires-Dist: nengo-extras (>=0.5) ; extra == 'tests'
Requires-Dist: pytest (>=5.0.0) ; extra == 'tests'
Requires-Dist: pytest-allclose (>=1.0.0) ; extra == 'tests'
Requires-Dist: pytest-cov (>=2.6.0) ; extra == 'tests'
Requires-Dist: pytest-plt (>=1.0.0) ; extra == 'tests'
Requires-Dist: pytest-rng (>=1.0.0) ; extra == 'tests'
Requires-Dist: pytest-xdist (>=2.0.0) ; extra == 'tests'
Requires-Dist: matplotlib (>=2.0) ; extra == 'tests'
